lennoxs30api/__init__.py
lennoxs30api/lennox_ble.py
lennoxs30api/lennox_equipment.py
lennoxs30api/lennox_errors.py
lennoxs30api/lennox_home.py
lennoxs30api/lennox_period.py
lennoxs30api/lennox_schedule.py
lennoxs30api/message_logger.py
lennoxs30api/metrics.py
lennoxs30api/s30api_async.py
lennoxs30api/s30exception.py
lennoxs30api/subscriber_base.py
lennoxs30api-0.2.19.dist-info/LICENSE
lennoxs30api-0.2.19.dist-info/METADATA
lennoxs30api-0.2.19.dist-info/WHEEL
lennoxs30api-0.2.19.dist-info/top_level.txt
lennoxs30api-0.2.19.dist-info/RECORD
