Metadata-Version: 2.1
Name: lennoxs30api
Version: 0.2.19
Summary: API Wrapper for Lennox S30 Cloud and LAN API
Home-page: https://github.com/PeteRager/lennoxs30api
Author: Pete Rage
Author-email: pete.rager@x.com
License: MIT
Classifier: Programming Language :: Python :: 3
Classifier: License :: OSI Approved :: MIT License
Classifier: Operating System :: OS Independent
License-File: LICENSE
Requires-Dist: aiohttp
